bacpypes3/__init__.py
bacpypes3/__main__.py
bacpypes3/apdu.py
bacpypes3/app.py
bacpypes3/appservice.py
bacpypes3/argparse.py
bacpypes3/basetypes.py
bacpypes3/cmd.py
bacpypes3/comm.py
bacpypes3/console.py
bacpypes3/constructeddata.py
bacpypes3/debugging.py
bacpypes3/errors.py
bacpypes3/netservice.py
bacpypes3/npdu.py
bacpypes3/object.py
bacpypes3/pdu.py
bacpypes3/primitivedata.py
bacpypes3/settings.py
bacpypes3/vendor.py
bacpypes3/ipv4/__init__.py
bacpypes3/ipv4/app.py
bacpypes3/ipv4/bvll.py
bacpypes3/ipv4/link.py
bacpypes3/ipv4/service.py
bacpypes3/ipv6/__init__.py
bacpypes3/ipv6/bvll.py
bacpypes3/ipv6/service.py
bacpypes3/json/__init__.py
bacpypes3/json/__main__.py
bacpypes3/json/util.py
bacpypes3/lib/__init__.py
bacpypes3/lib/batchread.py
bacpypes3/local/__init__.py
bacpypes3/local/analog.py
bacpypes3/local/binary.py
bacpypes3/local/cmd.py
bacpypes3/local/cov.py
bacpypes3/local/device.py
bacpypes3/local/event.py
bacpypes3/local/fault.py
bacpypes3/local/multistate.py
bacpypes3/local/networkport.py
bacpypes3/local/object.py
bacpypes3/local/oos.py
bacpypes3/local/schedule.py
bacpypes3/rdf/__init__.py
bacpypes3/rdf/__main__.py
bacpypes3/rdf/core.py
bacpypes3/rdf/util.py
bacpypes3/sc/__init__.py
bacpypes3/sc/bvll.py
bacpypes3/sc/service.py
bacpypes3/service/__init__.py
bacpypes3/service/cov.py
bacpypes3/service/device.py
bacpypes3/service/object.py
bacpypes3/vlan/__init__.py
bacpypes3/vlan/link.py
tests/__init__.py
tests/clocked_test.py
tests/conftest.py
tests/state_machine.py
tests/test_1.py
tests/test__template.py
tests/trapped_classes.py
tests/utilities.py
tests/test_app/__init__.py
tests/test_app/test_parse_reference.py
tests/test_app/test_read_write_api.py
tests/test_basetypes/__init__.py
tests/test_basetypes/test_datetime.py
tests/test_constructed_data/__init__.py
tests/test_constructed_data/test_any.py
tests/test_constructed_data/test_array.py
tests/test_constructed_data/test_choice.py
tests/test_constructed_data/test_list.py
bacpypes3-0.0.102.dist-info/METADATA
bacpypes3-0.0.102.dist-info/WHEEL
bacpypes3-0.0.102.dist-info/top_level.txt
bacpypes3-0.0.102.dist-info/RECORD
