Metadata-Version: 2.2
Name: bacpypes3
Version: 0.0.102
Summary: BACnet Communications Library
Home-page: https://github.com/JoelBender/bacpypes3
Author: Joel Bender
Author-email: joel@carrickbender.com
License: MIT
Classifier: Development Status :: 2 - Pre-Alpha
Classifier: Intended Audience :: Developers
Classifier: License :: OSI Approved :: BSD License
Classifier: Natural Language :: English
Classifier: Programming Language :: Python :: 3
Classifier: Programming Language :: Python :: 3.8
Dynamic: author
Dynamic: author-email
Dynamic: classifier
Dynamic: description
Dynamic: description-content-type
Dynamic: home-page
Dynamic: license
Dynamic: summary
